drizzlepac/processInput.py
drizzlepac/adrizzle.help
drizzlepac/buildmask.py
drizzlepac/staticMask.py
drizzlepac/findobj.py
drizzlepac/runsinglehap.py
drizzlepac/runmultihap.py
drizzlepac/version.py
drizzlepac/imgclasses.py
drizzlepac/pixtopix.py
drizzlepac/tweakback.py
drizzlepac/align.py
drizzlepac/irData.py
drizzlepac/mdzhandler.py
drizzlepac/pixtosky.help
drizzlepac/mapreg.py
drizzlepac/util.py
drizzlepac/buildwcs.py
drizzlepac/catalogs.py
drizzlepac/hapsequencer.py
drizzlepac/ablot.help
drizzlepac/mdriz.py
drizzlepac/imagefindpars.py
drizzlepac/config_testbed.py
drizzlepac/skytopix.py
drizzlepac/imagefindpars.help
drizzlepac/acsData.py
drizzlepac/run_hapsequencer.py
drizzlepac/__init__.py
drizzlepac/hapcatalog.py
drizzlepac/wfc3Data.py
drizzlepac/regfilter.py
drizzlepac/ablot.py
drizzlepac/runastrodriz.py
drizzlepac/createMedian.help
drizzlepac/sky.py
drizzlepac/outputimage.py
drizzlepac/linearfit.py
drizzlepac/resetbits.py
drizzlepac/updatenpol.py
drizzlepac/cdriz.cpython-311-darwin.so
drizzlepac/astrodrizzle.py
drizzlepac/tweakutils.py
drizzlepac/astrodrizzle.help
drizzlepac/minmed.py
drizzlepac/stisData.py
drizzlepac/wcs_functions.py
drizzlepac/wfpc2Data.py
drizzlepac/createMedian.py
drizzlepac/tweakreg.help
drizzlepac/pixtopix.help
drizzlepac/mapreg.help
drizzlepac/sky.help
drizzlepac/hapmultisequencer.py
drizzlepac/pixreplace.py
drizzlepac/skytopix.help
drizzlepac/make_custom_mosaic.py
drizzlepac/staticMask.help
drizzlepac/nicmosData.py
drizzlepac/imageObject.py
drizzlepac/refimagefindpars.py
drizzlepac/photeq.py
drizzlepac/drizCR.help
drizzlepac/drizCR.py
drizzlepac/pixtosky.py
drizzlepac/quickDeriv.py
drizzlepac/adrizzle.py
drizzlepac/updatehdr.py
drizzlepac/refimagefindpars.help
drizzlepac/tweakreg.py
drizzlepac/haputils/pandas_utils.py
drizzlepac/haputils/align_utils.py
drizzlepac/haputils/quality_analysis.py
drizzlepac/haputils/background_median.py
drizzlepac-3.10.0.dist-info/RECORD
drizzlepac-3.10.0.dist-info/WHEEL
drizzlepac-3.10.0.dist-info/entry_points.txt
drizzlepac-3.10.0.dist-info/top_level.txt
drizzlepac-3.10.0.dist-info/METADATA
drizzlepac-3.10.0.dist-info/licenses/LICENSE.txt
