Metadata-Version: 2.4
Name: drizzlepac
Version: 3.10.0
Summary:  HST image combination using the drizzle algorithm to combine astronomical images, to model image distortion, to remove cosmic rays, and generally to improve the fidelity of data in the final image. 
Author: Megan Sosey, Warren Hack, Christopher Hanley, Chris Sontag, Mihai Cara, Michael Dulude, Michele De La Pena, Steven Goldman
License: BSD 3-Clause License
Project-URL: tracker, https://github.com/spacetelescope/drizzlepac/issues
Project-URL: documentation, https://drizzlepac.readthedocs.io/en/latest
Project-URL: source, https://github.com/spacetelescope/drizzlepac
Classifier: Intended Audience :: Science/Research
Classifier: Topic :: Scientific/Engineering :: Astronomy
Classifier: License :: OSI Approved :: BSD License
Classifier: Operating System :: MacOS :: MacOS X
Classifier: Operating System :: POSIX
Classifier: Programming Language :: Python :: 3
Classifier: Programming Language :: Python :: 3 :: Only
Classifier: Programming Language :: Python :: 3.12
Classifier: Programming Language :: Python :: 3.11
Requires-Python: >=3.11
License-File: LICENSE.txt
Requires-Dist: astropy>=5.0.4
Requires-Dist: fitsblender>=0.4.2
Requires-Dist: scipy
Requires-Dist: matplotlib
Requires-Dist: stsci.tools>=4.0
Requires-Dist: stsci.image>=2.3.7
Requires-Dist: stsci.imagestats>=1.8.2
Requires-Dist: stsci.skypac>=1.0.9
Requires-Dist: stsci.stimage
Requires-Dist: stwcs>=1.7.4
Requires-Dist: tweakwcs>=0.8.7
Requires-Dist: stregion>=1.1.7
Requires-Dist: requests
Requires-Dist: scikit-learn>=0.20
Requires-Dist: simplify-polyline
Requires-Dist: bokeh
Requires-Dist: pandas
Requires-Dist: spherical_geometry>=1.2.22
Requires-Dist: astroquery>=0.4
Requires-Dist: astrocut<=0.9
Requires-Dist: photutils>=2.0.0
Requires-Dist: lxml
Requires-Dist: PyPDF2
Requires-Dist: scikit-image>=0.14.2
Requires-Dist: numpy>2.0
Provides-Extra: docs
Requires-Dist: sphinx; extra == "docs"
Requires-Dist: stsci_rtd_theme; extra == "docs"
Requires-Dist: packaging; extra == "docs"
Requires-Dist: tomli; extra == "docs"
Requires-Dist: numpydoc; extra == "docs"
Requires-Dist: sphinx_automodapi; extra == "docs"
Requires-Dist: graphviz; extra == "docs"
Requires-Dist: astrocut; extra == "docs"
Requires-Dist: tables; extra == "docs"
Provides-Extra: test
Requires-Dist: ci_watson; extra == "test"
Requires-Dist: crds; extra == "test"
Requires-Dist: pytest; extra == "test"
Requires-Dist: pytest-remotedata; extra == "test"
Dynamic: license-file
